src/__init__.py
src/apify_scrapy_migrator.py
src/create_files.py
apify_scrapy_migrator-0.0.3.dist-info/LICENSE
apify_scrapy_migrator-0.0.3.dist-info/METADATA
apify_scrapy_migrator-0.0.3.dist-info/WHEEL
apify_scrapy_migrator-0.0.3.dist-info/entry_points.txt
apify_scrapy_migrator-0.0.3.dist-info/top_level.txt
apify_scrapy_migrator-0.0.3.dist-info/RECORD
