Metadata-Version: 2.1
Name: apify-scrapy-migrator
Version: 0.0.3
Summary: Migrates scrapy project to Apify platform
Home-page: https://github.com/spiduso/apify-scrapy-migrator
Author: Hoang Anh Tuan
Author-email: hoang.dusan@gmail.com
Project-URL: Bug Tracker, https://github.com/spiduso/apify-scrapy-migrator/issues
Classifier: Programming Language :: Python :: 3
Classifier: Operating System :: OS Independent
Requires-Python: >=3.9
License-File: LICENSE
Requires-Dist: pipreqs
Requires-Dist: requests (==2.26.0)
